airmaps/__init__.py
airmaps/dags/build_coastline.py
airmaps/dags/build_maps.py
airmaps/dags/update_planet.py
airmaps/instruments/settings.py
airmaps/instruments/storage.py
airmaps/instruments/utils.py
airmaps/var/etc/airmaps.ini.default
omim_airmaps-10.3.0rc2.dist-info/METADATA
omim_airmaps-10.3.0rc2.dist-info/WHEEL
omim_airmaps-10.3.0rc2.dist-info/top_level.txt
omim_airmaps-10.3.0rc2.dist-info/RECORD
