Metadata-Version: 2.1
Name: omim-airmaps
Version: 10.3.0rc2
Summary: This package contains tools for generating maps with Apache Airflow.
Home-page: https://github.com/mapsme
Author: My.com B.V. (Mail.Ru Group)
Author-email: dev@maps.me
License: UNKNOWN
Platform: UNKNOWN
Classifier: Programming Language :: Python :: 3
Classifier: License :: OSI Approved :: Apache Software License
Requires-Python: >=3.6
Requires-Dist: omim-data-all (==10.3.0rc2)
Requires-Dist: omim-maps-generator (==10.3.0rc2)
Requires-Dist: apache-airflow[postgres] (==1.10.10)
Requires-Dist: psycopg2-binary (==2.8.4)
Requires-Dist: cryptography (==2.8)
Requires-Dist: webdavclient (==1.0.8)
